covmatic_robotmanager/EvaHelper.py
covmatic_robotmanager/EvaLockThread.py
covmatic_robotmanager/__init__.py
covmatic_robotmanager/api.py
covmatic_robotmanager/calibrator.py
covmatic_robotmanager/config.py
covmatic_robotmanager/gripper.py
covmatic_robotmanager/main.py
covmatic_robotmanager/movement.py
covmatic_robotmanager/positions.py
covmatic_robotmanager/robot.py
covmatic_robotmanager/robot_manager.py
covmatic_robotmanager/setup.py
covmatic_robotmanager/singleton.py
covmatic_robotmanager/toolpath.py
covmatic_robotmanager/utils.py
covmatic_robotmanager/templates/Covmatic-robotmanager_Icon.ico
covmatic_robotmanager/templates/Covmatic-robotmanager_Icon.png
covmatic_robotmanager/templates/covmatic.desktop
covmatic_robotmanager-0.0.6.dist-info/METADATA
covmatic_robotmanager-0.0.6.dist-info/WHEEL
covmatic_robotmanager-0.0.6.dist-info/entry_points.txt
covmatic_robotmanager-0.0.6.dist-info/licenses/LICENSE
covmatic_robotmanager-0.0.6.dist-info/RECORD
