Metadata-Version: 2.1
Name: covmatic-robotmanager
Version: 0.0.6
Summary: Covmatic Robot Manager is a robotic arm manager for action requested by other robots
Project-URL: Homepage, https://github.com/ASST-Bergamo-Est/covmatic-robotmanager
Project-URL: Source, https://github.com/ASST-Bergamo-Est/covmatic-robotmanager
Author-email: Agostino Facotti <agostino.facotti@asst-bergamoest.it>
License-File: LICENSE
Keywords: automation,biology,lab,robotics
Classifier: Development Status :: 4 - Beta
Classifier: License :: OSI Approved :: MIT License
Classifier: Operating System :: OS Independent
Classifier: Programming Language :: Python :: 3
Requires-Python: >=3.7
Requires-Dist: configargparse
Requires-Dist: evasdk
Requires-Dist: flask
Requires-Dist: flask-restful
Requires-Dist: pywin32; platform_system == 'Windows'
Requires-Dist: waitress
Requires-Dist: winshell; platform_system == 'Windows'
